{"exchange": "HOSE", "shortName": "Techcombank", "industryID": 289, "industryIDv2": "8355", "industryIdLevel2": "8300", "industryIdLevel4": "8355", "industry": "Ng\u00e2n h\u00e0ng", "industryEn": "Banks", "establishedYear": "1993", "noEmployees": 11848, "noShareholders": 1901, "foreignPercent": 0.225, "website": "https://techcombank.com", "stockRating": 3.1, "deltaInWeek": -0.022, "deltaInMonth": 0.023, "deltaInYear": 0.228, "outstandingShare": 7064.9, "issueShare": 7064.9, "companyType": "NH", "ticker": "TCB"}